{
  "id": "gavang",
  "name": "⚽ GaVangTV",
  "description": "Trực tiếp bóng đá GaVangTV",
  "color": "#FFD700",
  "url": "",
  "image": {
    "type": "cover",
    "url": "https://cdn.fastestcdn-global.com/seo-gavangtv-v4/icons/logo.png"
  },
  "groups": [
    {
      "id": "live",
      "name": "🔴 LIVE",
      "channels": [
        {
          "id": "1l4rjnh9n39zm7v",
          "name": "Portland Thorns FC Women 1 - 0 Bay FC (w)",
          "type": "single",
          "display": "thumbnail-only",
          "image": {
            "display": "cover",
            "shape": "rectangle",
            "url": "https://raidenfb-card.vercel.app/api/card?t1=Portland+Thorns+FC+Women+1+-+0+Bay+FC+%28w%29&t2=&live=1&lg=United+States+Women%27s+National+Soccer+League&l1=https%3A%2F%2Fimg.sports-data.online%2Ffootball%2Fteam%2F2f1e551d0f4223fd99fc446a41227423.png&s=vs",
            "width": 600,
            "height": 320
          },
          "labels": [
            {
              "text": "🔴 LIVE",
              "position": "top-left",
              "color": "#ff0000",
              "text_color": "#ffffff"
            }
          ],
          "sources": [
            {
              "contents": [
                {
                  "streams": [
                    {
                      "id": "default",
                      "name": "Stream",
                      "stream_links": [
                        {
                          "id": "hls",
                          "type": "hls",
                          "url": "https://www3.f2k3.shop/live/ffde3bbfbfb0ae45c9dcbe37d529183a/playlist.m3u8"
                        }
                      ]
                    }
                  ]
                }
              ]
            }
          ]
        },
        {
          "id": "23xmvkh6y5wxqg8",
          "name": "Atletico Junior Barranquilla 3 - 1 Sporting Cristal",
          "type": "single",
          "display": "thumbnail-only",
          "image": {
            "display": "cover",
            "shape": "rectangle",
            "url": "https://raidenfb-card.vercel.app/api/card?t1=Atletico+Junior+Barranquilla+3+-+1+Sporting+Cristal&t2=&live=1&blv=G%C3%A0+Si%C3%AAu+%C4%90%C3%B4&lg=CONMEBOL+Copa+Libertadores&l1=https%3A%2F%2Fimg.sports-data.online%2Ffootball%2Fteam%2Ffd3230c7fa4ad7bde28c640f2f32ca43.png&s=vs",
            "width": 600,
            "height": 320
          },
          "labels": [
            {
              "text": "🔴 LIVE",
              "position": "top-left",
              "color": "#ff0000",
              "text_color": "#ffffff"
            },
            {
              "text": "👨‍💼 Gà Siêu Đô",
              "position": "bottom-left",
              "color": "#FFD700",
              "text_color": "#ffffff"
            }
          ],
          "sources": [
            {
              "contents": [
                {
                  "streams": [
                    {
                      "id": "default",
                      "name": "BLV Gà Siêu Đô",
                      "stream_links": [
                        {
                          "id": "hls",
                          "type": "hls",
                          "url": "https://www3.f2k3.shop/live/ca5923452d9c2e3fc647265342ec1560/playlist.m3u8"
                        }
                      ]
                    }
                  ]
                }
              ]
            }
          ]
        },
        {
          "id": "4jwq2ghn5zy1m0v",
          "name": "Guangdong Guangzhou Power U20 2 - 1 Beijing Guoan U20",
          "type": "single",
          "display": "thumbnail-only",
          "image": {
            "display": "cover",
            "shape": "rectangle",
            "url": "https://raidenfb-card.vercel.app/api/card?t1=Guangdong+Guangzhou+Power+U20+2+-+1+Beijing+Guoan+U20&t2=&live=1&lg=Chinese+Football+Assorciation+U-20+League&l1=https%3A%2F%2Fimg.sports-data.online%2Ffootball%2Fteam%2F2bdbe347bf862754fcbc5cc12c7ad14c.png&s=vs",
            "width": 600,
            "height": 320
          },
          "labels": [
            {
              "text": "🔴 LIVE",
              "position": "top-left",
              "color": "#ff0000",
              "text_color": "#ffffff"
            }
          ],
          "sources": [
            {
              "contents": [
                {
                  "streams": [
                    {
                      "id": "default",
                      "name": "Stream",
                      "stream_links": [
                        {
                          "id": "hls",
                          "type": "hls",
                          "url": "https://www3.f2k3.shop/live/d77faec23476e58bf68e092e50e97a7b/playlist.m3u8"
                        }
                      ]
                    }
                  ]
                }
              ]
            }
          ]
        },
        {
          "id": "dn1m1ghlgpy2moe",
          "name": "Hubei Istar U20 1 - 2 Shanghai Shenhua U20",
          "type": "single",
          "display": "thumbnail-only",
          "image": {
            "display": "cover",
            "shape": "rectangle",
            "url": "https://raidenfb-card.vercel.app/api/card?t1=Hubei+Istar+U20+1+-+2+Shanghai+Shenhua+U20&t2=&live=1&lg=Chinese+Football+Assorciation+U-20+League&l1=https%3A%2F%2Fimg.sports-data.online%2Ffootball%2Fteam%2F505e6c66e652c8500754099eb424c161.png&s=vs",
            "width": 600,
            "height": 320
          },
          "labels": [
            {
              "text": "🔴 LIVE",
              "position": "top-left",
              "color": "#ff0000",
              "text_color": "#ffffff"
            }
          ],
          "sources": [
            {
              "contents": [
                {
                  "streams": [
                    {
                      "id": "default",
                      "name": "Stream",
                      "stream_links": [
                        {
                          "id": "hls",
                          "type": "hls",
                          "url": "https://www3.f2k3.shop/live/178197c4acbaff9360d22c9b0ffea52f/playlist.m3u8"
                        }
                      ]
                    }
                  ]
                }
              ]
            }
          ]
        },
        {
          "id": "jw2r09hkg6y3rz8",
          "name": "Henan FC U20 1 - 0 Lanzhou Longyuan Athletic U20",
          "type": "single",
          "display": "thumbnail-only",
          "image": {
            "display": "cover",
            "shape": "rectangle",
            "url": "https://raidenfb-card.vercel.app/api/card?t1=Henan+FC+U20+1+-+0+Lanzhou+Longyuan+Athletic+U20&t2=&live=1&lg=Chinese+Football+Assorciation+U-20+League&l1=https%3A%2F%2Fimg.sports-data.online%2Ffootball%2Fteam%2F7571fdec060b883ba9fb481fcbe98069.png&s=vs",
            "width": 600,
            "height": 320
          },
          "labels": [
            {
              "text": "🔴 LIVE",
              "position": "top-left",
              "color": "#ff0000",
              "text_color": "#ffffff"
            }
          ],
          "sources": [
            {
              "contents": [
                {
                  "streams": [
                    {
                      "id": "default",
                      "name": "Stream",
                      "stream_links": [
                        {
                          "id": "hls",
                          "type": "hls",
                          "url": "https://www3.f2k3.shop/live/5dce23e7cdfa8666b7f2eb2cc2b7e912/playlist.m3u8"
                        }
                      ]
                    }
                  ]
                }
              ]
            }
          ]
        },
        {
          "id": "k82rekhgj0pxrep",
          "name": "Zhejiang Professional FC U20 2 - 0 Qingdao Hainiu U20",
          "type": "single",
          "display": "thumbnail-only",
          "image": {
            "display": "cover",
            "shape": "rectangle",
            "url": "https://raidenfb-card.vercel.app/api/card?t1=Zhejiang+Professional+FC+U20+2+-+0+Qingdao+Hainiu+U20&t2=&live=1&lg=Chinese+Football+Assorciation+U-20+League&l1=https%3A%2F%2Fimg.sports-data.online%2Ffootball%2Fteam%2F3746e3fba62790b0f2694bf858180c04.png&s=vs",
            "width": 600,
            "height": 320
          },
          "labels": [
            {
              "text": "🔴 LIVE",
              "position": "top-left",
              "color": "#ff0000",
              "text_color": "#ffffff"
            }
          ],
          "sources": [
            {
              "contents": [
                {
                  "streams": [
                    {
                      "id": "default",
                      "name": "Stream",
                      "stream_links": [
                        {
                          "id": "hls",
                          "type": "hls",
                          "url": "https://www3.f2k3.shop/live/eeae62e3aaa68c54205b5208b2dd7ff6/playlist.m3u8"
                        }
                      ]
                    }
                  ]
                }
              ]
            }
          ]
        },
        {
          "id": "zp5rzghg32g7q82",
          "name": "Angel City FC Women 1 - 1 Kansas City Current Women",
          "type": "single",
          "display": "thumbnail-only",
          "image": {
            "display": "cover",
            "shape": "rectangle",
            "url": "https://raidenfb-card.vercel.app/api/card?t1=Angel+City+FC+Women+1+-+1+Kansas+City+Current+Women&t2=&live=1&lg=United+States+Women%27s+National+Soccer+League&l1=https%3A%2F%2Fimg.sports-data.online%2Ffootball%2Fteam%2Fbcedf53b78b380edaeb5b36dce2515ff.png&s=vs",
            "width": 600,
            "height": 320
          },
          "labels": [
            {
              "text": "🔴 LIVE",
              "position": "top-left",
              "color": "#ff0000",
              "text_color": "#ffffff"
            }
          ],
          "sources": [
            {
              "contents": [
                {
                  "streams": [
                    {
                      "id": "default",
                      "name": "Stream",
                      "stream_links": [
                        {
                          "id": "hls",
                          "type": "hls",
                          "url": "https://www3.f2k3.shop/live/4755bdd1a27430084c59e2884eb1d87a/playlist.m3u8"
                        }
                      ]
                    }
                  ]
                }
              ]
            }
          ]
        },
        {
          "id": "4wyrn4h65y1kq86",
          "name": "Montego Bay Utd 0 - 0 Cavalier FC",
          "type": "single",
          "display": "thumbnail-only",
          "image": {
            "display": "cover",
            "shape": "rectangle",
            "url": "https://raidenfb-card.vercel.app/api/card?t1=Montego+Bay+Utd+0+-+0+Cavalier+FC&t2=&live=1&lg=Jamaica+Premier+League&l1=https%3A%2F%2Fimg.sports-data.online%2Ffootball%2Fteam%2Fac96fe7fc9b7f370a318b00c980eb323.png&s=vs",
            "width": 600,
            "height": 320
          },
          "labels": [
            {
              "text": "🔴 LIVE",
              "position": "top-left",
              "color": "#ff0000",
              "text_color": "#ffffff"
            }
          ],
          "sources": [
            {
              "contents": [
                {
                  "streams": [
                    {
                      "id": "default",
                      "name": "Stream",
                      "stream_links": [
                        {
                          "id": "hls",
                          "type": "hls",
                          "url": "https://www3.f2k3.shop/live/2b391b7a997f3cfec9973e37934ff29b/playlist.m3u8"
                        }
                      ]
                    }
                  ]
                }
              ]
            }
          ]
        },
        {
          "id": "y0or5jh8w9o3qwz",
          "name": "Washington Spirit Women 0 - 0 Pachuca Women",
          "type": "single",
          "display": "thumbnail-only",
          "image": {
            "display": "cover",
            "shape": "rectangle",
            "url": "https://raidenfb-card.vercel.app/api/card?t1=Washington+Spirit+Women+0+-+0+Pachuca+Women&t2=&live=1&lg=CNCF+WCC&l1=https%3A%2F%2Fimg.sports-data.online%2Ffootball%2Fteam%2F76c34622a2b9c6ccdf6d2c363e255cd3.png&s=vs",
            "width": 600,
            "height": 320
          },
          "labels": [
            {
              "text": "🔴 LIVE",
              "position": "top-left",
              "color": "#ff0000",
              "text_color": "#ffffff"
            }
          ],
          "sources": [
            {
              "contents": [
                {
                  "streams": [
                    {
                      "id": "default",
                      "name": "Stream",
                      "stream_links": [
                        {
                          "id": "hls",
                          "type": "hls",
                          "url": "https://www3.f2k3.shop/live/24eeea98d20b1fccadb7f884c89d3042/playlist.m3u8"
                        }
                      ]
                    }
                  ]
                }
              ]
            }
          ]
        }
      ],
      "display": "vertical",
      "grid_number": 1
    }
  ],
  "option": {
    "save_history": false,
    "save_search_history": false,
    "save_wishlist": false
  }
}