{
  "id": "gavang",
  "name": "⚽ GaVangTV",
  "description": "Trực tiếp bóng đá GaVangTV",
  "color": "#FFD700",
  "url": "",
  "image": {
    "type": "cover",
    "url": "https://cdn.fastestcdn-global.com/seo-gavangtv-v4/icons/logo.png"
  },
  "groups": [
    {
      "id": "live",
      "name": "🔴 LIVE",
      "channels": [
        {
          "id": "2y8m4zh5w55gql0",
          "name": "Colorado Springs 2 - 2 Orange County SC",
          "type": "single",
          "display": "thumbnail-only",
          "image": {
            "display": "cover",
            "shape": "rectangle",
            "url": "https://raidenfb-card.vercel.app/api/card?t1=Colorado+Springs+2+-+2+Orange+County+SC&t2=&live=1&lg=USL+Championship&l1=https%3A%2F%2Fimg.rapid-api.icu%2Ffootball%2Fteam%2Ff6d64820dd24900dee27c032de34be01%2Fimage%2Fsmall%3Fv%3D1768601124&s=vs",
            "width": 600,
            "height": 320
          },
          "labels": [
            {
              "text": "🔴 LIVE",
              "position": "top-left",
              "color": "#ff0000",
              "text_color": "#ffffff"
            }
          ],
          "sources": [
            {
              "contents": [
                {
                  "streams": [
                    {
                      "id": "default",
                      "name": "Stream",
                      "stream_links": [
                        {
                          "id": "hls",
                          "type": "hls",
                          "url": "https://live.rapidlive.shop/live/0d4abbb0df607c12dccd32a22f441c37/playlist.m3u8"
                        }
                      ]
                    }
                  ]
                }
              ]
            }
          ]
        },
        {
          "id": "ednm9whwp060ryo",
          "name": "Weston Workers Reserves 0 - 3 Valentine Phoenix Reserves",
          "type": "single",
          "display": "thumbnail-only",
          "image": {
            "display": "cover",
            "shape": "rectangle",
            "url": "https://raidenfb-card.vercel.app/api/card?t1=Weston+Workers+Reserves+0+-+3+Valentine+Phoenix+Reserves&t2=&live=1&lg=Australia+Northern+New+South+Wales+Reserves+League&l1=https%3A%2F%2Fimg.rapid-api.icu%2Ffootball%2Fteam%2F41044cec6544d331601512a0e92aacb2%2Fimage%2Fsmall%3Fv%3D1768601124&s=vs",
            "width": 600,
            "height": 320
          },
          "labels": [
            {
              "text": "🔴 LIVE",
              "position": "top-left",
              "color": "#ff0000",
              "text_color": "#ffffff"
            }
          ],
          "sources": [
            {
              "contents": [
                {
                  "streams": [
                    {
                      "id": "default",
                      "name": "Stream",
                      "stream_links": [
                        {
                          "id": "hls",
                          "type": "hls",
                          "url": "https://live.rapidlive.shop/live/89e1ec77e0d655e71be7a7ad3892785e/playlist.m3u8"
                        }
                      ]
                    }
                  ]
                }
              ]
            }
          ]
        },
        {
          "id": "3glrw7hngpn3qdy",
          "name": "Devonport Strikers Women 3 - 0 Kingborough Lions Women",
          "type": "single",
          "display": "thumbnail-only",
          "image": {
            "display": "cover",
            "shape": "rectangle",
            "url": "https://raidenfb-card.vercel.app/api/card?t1=Devonport+Strikers+Women+3+-+0+Kingborough+Lions+Women&t2=&live=1&lg=Australia+Tasmania+Women%27s+Premier+League&l1=https%3A%2F%2Fimg.rapid-api.icu%2Ffootball%2Fteam%2F9a6d63a2e5235de190e576eff904bf6e%2Fimage%2Fsmall%3Fv%3D1768601124&s=vs",
            "width": 600,
            "height": 320
          },
          "labels": [
            {
              "text": "🔴 LIVE",
              "position": "top-left",
              "color": "#ff0000",
              "text_color": "#ffffff"
            }
          ],
          "sources": [
            {
              "contents": [
                {
                  "streams": [
                    {
                      "id": "default",
                      "name": "Stream",
                      "stream_links": [
                        {
                          "id": "hls",
                          "type": "hls",
                          "url": "https://live.rapidlive.shop/live/87922638e708f9cf5fd161336127f36f/playlist.m3u8"
                        }
                      ]
                    }
                  ]
                }
              ]
            }
          ]
        },
        {
          "id": "4wyrn4h650jzq86",
          "name": "Auckland FC Reserves 2 - 0 Bula FC",
          "type": "single",
          "display": "thumbnail-only",
          "image": {
            "display": "cover",
            "shape": "rectangle",
            "url": "https://raidenfb-card.vercel.app/api/card?t1=Auckland+FC+Reserves+2+-+0+Bula+FC&t2=&live=1&lg=OFC+Pro+League&l1=https%3A%2F%2Fimg.rapid-api.icu%2Ffootball%2Fteam%2F11687c18097f7743c43fd55ee90af610%2Fimage%2Fsmall%3Fv%3D1768601124&s=vs",
            "width": 600,
            "height": 320
          },
          "labels": [
            {
              "text": "🔴 LIVE",
              "position": "top-left",
              "color": "#ff0000",
              "text_color": "#ffffff"
            }
          ],
          "sources": [
            {
              "contents": [
                {
                  "streams": [
                    {
                      "id": "default",
                      "name": "Stream",
                      "stream_links": [
                        {
                          "id": "hls",
                          "type": "hls",
                          "url": "https://live.rapidlive.shop/live/d3309e24d5470ddfc6f531e3afd82da6/playlist.m3u8"
                        }
                      ]
                    }
                  ]
                }
              ]
            }
          ]
        },
        {
          "id": "vjxm8ghe7welr6o",
          "name": "OConnor Knights U23 1 - 5 Monaro Panthers U23",
          "type": "single",
          "display": "thumbnail-only",
          "image": {
            "display": "cover",
            "shape": "rectangle",
            "url": "https://raidenfb-card.vercel.app/api/card?t1=OConnor+Knights+U23+1+-+5+Monaro+Panthers+U23&t2=&live=1&lg=Australia+Capital+Territory+U23+League&l1=https%3A%2F%2Fimg.rapid-api.icu%2Ffootball%2Fteam%2F3f5fc99395c1ae02d9741ca72babbc6a%2Fimage%2Fsmall%3Fv%3D1768601124&s=vs",
            "width": 600,
            "height": 320
          },
          "labels": [
            {
              "text": "🔴 LIVE",
              "position": "top-left",
              "color": "#ff0000",
              "text_color": "#ffffff"
            }
          ],
          "sources": [
            {
              "contents": [
                {
                  "streams": [
                    {
                      "id": "default",
                      "name": "Stream",
                      "stream_links": [
                        {
                          "id": "hls",
                          "type": "hls",
                          "url": "https://live.rapidlive.shop/live/1f26b1f40ea78584ddd1be5d8915f9af/playlist.m3u8"
                        }
                      ]
                    }
                  ]
                }
              ]
            }
          ]
        },
        {
          "id": "ednm9whwp07oryo",
          "name": "Flinders United Women 0 - 5 Salisbury Inter Women",
          "type": "single",
          "display": "thumbnail-only",
          "image": {
            "display": "cover",
            "shape": "rectangle",
            "url": "https://raidenfb-card.vercel.app/api/card?t1=Flinders+United+Women+0+-+5+Salisbury+Inter+Women&t2=&live=1&lg=South+Australia+Women%27s+Premier+League&l1=https%3A%2F%2Fimg.rapid-api.icu%2Ffootball%2Fteam%2F9ef6137ef748e9388337864cf5590930%2Fimage%2Fsmall%3Fv%3D1768601124&s=vs",
            "width": 600,
            "height": 320
          },
          "labels": [
            {
              "text": "🔴 LIVE",
              "position": "top-left",
              "color": "#ff0000",
              "text_color": "#ffffff"
            }
          ],
          "sources": [
            {
              "contents": [
                {
                  "streams": [
                    {
                      "id": "default",
                      "name": "Stream",
                      "stream_links": [
                        {
                          "id": "hls",
                          "type": "hls",
                          "url": "https://live.rapidlive.shop/live/167f136b76e901cc0a488cb029498761/playlist.m3u8"
                        }
                      ]
                    }
                  ]
                }
              ]
            }
          ]
        },
        {
          "id": "k82rekhg05lvrep",
          "name": "Albirex Niigata Ladies 0 - 2 Nojima Stella Kanagawa Sagamihara",
          "type": "single",
          "display": "thumbnail-only",
          "image": {
            "display": "cover",
            "shape": "rectangle",
            "url": "https://raidenfb-card.vercel.app/api/card?t1=Albirex+Niigata+Ladies+0+-+2+Nojima+Stella+Kanagawa+Sagamihara&t2=&live=1&lg=Women+Empowerment+League&l1=https%3A%2F%2Fimg.rapid-api.icu%2Ffootball%2Fteam%2F2b37871f130ecefc8aed2fa701c1bd30%2Fimage%2Fsmall%3Fv%3D1768601124&s=vs",
            "width": 600,
            "height": 320
          },
          "labels": [
            {
              "text": "🔴 LIVE",
              "position": "top-left",
              "color": "#ff0000",
              "text_color": "#ffffff"
            }
          ],
          "sources": [
            {
              "contents": [
                {
                  "streams": [
                    {
                      "id": "default",
                      "name": "Stream",
                      "stream_links": [
                        {
                          "id": "hls",
                          "type": "hls",
                          "url": "https://live.rapidlive.shop/live/0cdcac1ca5e665b7d644ed8d6e62b36a/playlist.m3u8"
                        }
                      ]
                    }
                  ]
                }
              ]
            }
          ]
        },
        {
          "id": "pxwrxlhy0gdzryk",
          "name": "Melbourne City Women 1 - 0 Melbourne Victory Women",
          "type": "single",
          "display": "thumbnail-only",
          "image": {
            "display": "cover",
            "shape": "rectangle",
            "url": "https://raidenfb-card.vercel.app/api/card?t1=Melbourne+City+Women+1+-+0+Melbourne+Victory+Women&t2=&live=1&blv=G%C3%A0+Si%C3%AAu+S%C3%BAp&lg=Australia+W-League&l1=https%3A%2F%2Fimg.rapid-api.icu%2Ffootball%2Fteam%2F8e4ee379c696e9fdc87bbc192766c199%2Fimage%2Fsmall%3Fv%3D1768601124&s=vs",
            "width": 600,
            "height": 320
          },
          "labels": [
            {
              "text": "🔴 LIVE",
              "position": "top-left",
              "color": "#ff0000",
              "text_color": "#ffffff"
            },
            {
              "text": "👨‍💼 Gà Siêu Súp",
              "position": "bottom-left",
              "color": "#FFD700",
              "text_color": "#ffffff"
            }
          ],
          "sources": [],
          "enable_detail": false
        }
      ],
      "display": "vertical",
      "grid_number": 1
    }
  ],
  "option": {
    "save_history": false,
    "save_search_history": false,
    "save_wishlist": false
  }
}